flexibox/__init__.py
flexibox/driver.py
flexibox/configurations/__init__.py
flexibox/configurations/downloader_config.ini
flexibox/core/__init__.py
flexibox/core/browser_controller.py
flexibox/core/browser_object.py
flexibox/core/logger.py
flexibox/core/utility.py
flexibox/generic_functions/__init__.py
flexibox/generic_functions/chrome_object.py
flexibox/generic_functions/gecko_object.py
flexibox/generic_functions/opera_object.py
flexibox/generic_functions/phantom_object.py
flexibox/generic_functions/remotechrome_object.py
flexibox/generic_functions/remotegecko_object.py
flexibox/generic_functions/remotephantom_object.py
flexibox/generic_functions/safari_object.py
flexibox/standalonedriverobject/__init__.py
flexibox/standalonedriverobject/chromedriver.py
flexibox/standalonedriverobject/geckodriver.py
flexibox/standalonedriverobject/operadriver.py
flexibox/standalonedriverobject/phantomjsdriver.py
flexibox/utility/__init__.py
flexibox/utility/main.py
flexibox/utility/os_type.py
flexibox-1.0.1.dist-info/LICENSE.txt
flexibox-1.0.1.dist-info/METADATA
flexibox-1.0.1.dist-info/WHEEL
flexibox-1.0.1.dist-info/entry_points.txt
flexibox-1.0.1.dist-info/top_level.txt
flexibox-1.0.1.dist-info/RECORD
