Metadata-Version: 2.1
Name: flexibox
Version: 1.0.1
Summary: A single box of functionalities for a selenium project
Home-page: https://github.com/flu-x/Flexibox
Author: Soumyajit Basu
Author-email: soumyajit.basu62@gmail.com
License: UNKNOWN
Download-URL: https://github.com/flu-x/Flexibox/archive/1.0.1.tar.gz
Platform: UNKNOWN
Classifier: Intended Audience :: Information Technology
Classifier: Intended Audience :: Developers
Classifier: Development Status :: 5 - Production/Stable
Classifier: Programming Language :: Python :: 2
Classifier: Programming Language :: Python :: 2.6
Classifier: Programming Language :: Python :: 2.7
Classifier: Programming Language :: Python :: 3.7
Classifier: License :: OSI Approved :: MIT License
Classifier: Operating System :: MacOS :: MacOS X
Classifier: Operating System :: POSIX
Classifier: Topic :: Software Development :: Quality Assurance
Classifier: Topic :: Software Development :: Testing
Requires-Dist: requests
Requires-Dist: wget
Requires-Dist: selenium
